zeusback/__init__.py
zeusback/core.py
zeusback-2.1.dist-info/METADATA
zeusback-2.1.dist-info/WHEEL
zeusback-2.1.dist-info/entry_points.txt
zeusback-2.1.dist-info/top_level.txt
zeusback-2.1.dist-info/RECORD
