Metadata-Version: 2.2
Name: zeusback
Version: 2.1
Summary: A tool to fetch archived files from Wayback Machine
Home-page: https://github.com/zeusvuln/zeusback
Author: ZeUsVuLn (Hesham)
Author-email: he4am3id66@gmail.com
Requires-Dist: colorama
Requires-Dist: requests
Requires-Dist: validators
Dynamic: author
Dynamic: author-email
Dynamic: home-page
Dynamic: requires-dist
Dynamic: summary
